cidc_schemas/__init__.py
cidc_schemas/cli.py
cidc_schemas/constants.py
cidc_schemas/json_validation.py
cidc_schemas/migrations.py
cidc_schemas/template.py
cidc_schemas/template_reader.py
cidc_schemas/template_writer.py
cidc_schemas/unprism.py
cidc_schemas/util.py
cidc_schemas/metaschema/strict_meta_schema.json
cidc_schemas/pipeline_configs/rna_level1_analysis_config.yaml.j2
cidc_schemas/prism/__init__.py
cidc_schemas/prism/constants.py
cidc_schemas/prism/core.py
cidc_schemas/prism/extra_metadata.py
cidc_schemas/prism/merger.py
cidc_schemas/prism/pipelines.py
cidc_schemas/schemas/aliquot.json
cidc_schemas/schemas/clinical_data.json
cidc_schemas/schemas/clinical_trial.json
cidc_schemas/schemas/participant.json
cidc_schemas/schemas/sample.json
cidc_schemas/schemas/shipping_core.json
cidc_schemas/schemas/artifacts/artifact_bam.json
cidc_schemas/schemas/artifacts/artifact_bam_bai.json
cidc_schemas/schemas/artifacts/artifact_bed.json
cidc_schemas/schemas/artifacts/artifact_bigwig.json
cidc_schemas/schemas/artifacts/artifact_binary.json
cidc_schemas/schemas/artifacts/artifact_clinical_csv.json
cidc_schemas/schemas/artifacts/artifact_clinical_docx.json
cidc_schemas/schemas/artifacts/artifact_clinical_xlsx.json
cidc_schemas/schemas/artifacts/artifact_cncf.json
cidc_schemas/schemas/artifacts/artifact_cns.json
cidc_schemas/schemas/artifacts/artifact_core.json
cidc_schemas/schemas/artifacts/artifact_csv.json
cidc_schemas/schemas/artifacts/artifact_elisa_xlsx.json
cidc_schemas/schemas/artifacts/artifact_fastq_gz.json
cidc_schemas/schemas/artifacts/artifact_fcs.json
cidc_schemas/schemas/artifacts/artifact_file.json
cidc_schemas/schemas/artifacts/artifact_gz.json
cidc_schemas/schemas/artifacts/artifact_image.json
cidc_schemas/schemas/artifacts/artifact_jpg.json
cidc_schemas/schemas/artifacts/artifact_json.json
cidc_schemas/schemas/artifacts/artifact_junction.json
cidc_schemas/schemas/artifacts/artifact_log.json
cidc_schemas/schemas/artifacts/artifact_maf.json
cidc_schemas-0.26.23.dist-info/AUTHORS.rst
cidc_schemas-0.26.23.dist-info/LICENSE
cidc_schemas-0.26.23.dist-info/METADATA
cidc_schemas-0.26.23.dist-info/WHEEL
cidc_schemas-0.26.23.dist-info/entry_points.txt
cidc_schemas-0.26.23.dist-info/top_level.txt
cidc_schemas-0.26.23.dist-info/RECORD
