Metadata-Version: 2.1
Name: cidc-schemas
Version: 0.26.23
Summary: The CIDC data model and tools for working with it.
Home-page: https://github.com/CIMAC-CIDC/schemas
Author: James Lindsay
Author-email: jlindsay@jimmy.harvard.edu
License: MIT license
Keywords: cidc_schemas
Classifier: Development Status :: 2 - Pre-Alpha
Classifier: Intended Audience :: Developers
Classifier: License :: OSI Approved :: MIT License
Classifier: Natural Language :: English
Classifier: Programming Language :: Python :: 3.6
Classifier: Programming Language :: Python :: 3.7
Requires-Python: >=3.6
License-File: LICENSE
License-File: AUTHORS.rst
Requires-Dist: dateparser (==1.1.4)
Requires-Dist: xlsxwriter (==1.1.6)
Requires-Dist: argparse (==1.1)
Requires-Dist: pyyaml (~=5.1)
Requires-Dist: jsonschema (==3.0.1)
Requires-Dist: openpyxl (==3.0.7)
Requires-Dist: jsonmerge (==1.6.1)
Requires-Dist: deepdiff (~=4.3.0)
Requires-Dist: jsonpointer (==2.0)
Requires-Dist: pandas (==1.2.4)
Requires-Dist: jinja2 (~=3.0.3)
Requires-Dist: cidc-ngs-pipeline-api (==0.1.23)
Requires-Dist: markupsafe (==2.0.1)
Requires-Dist: regex (==2022.3.2)
